{
  "go": {
    "subtitle": "Go",
    "about": "Go is an open source programming language that makes it easy to build simple, reliable, and efficient software.",
    "site": "http://golang.org",
    "image": "go.jpg",
    "partners": [
      {
        "site" : "GopherCasts",
        "site_url": "https://gophercasts.io",
        "image": "gophercasts.jpg",
        "videos": [
          {
            "title": "Getting Started with Go",
            "description": "How to setup your environment and write a Hello World application using the Go programming language.",
            "duration": "3:14",
            "url": "https://gophercasts.io/lessons/1-getting-started-with-go"
          },
          {
            "title": "Go Language Basics",
            "description": "In this episode Jeremy covers the basics of variables, functions and loops in Go.",
            "duration": "5:49",
            "url": "https://gophercasts.io/lessons/2-go-language-basics"
          }
        ]
      }
    ]
  },
  "nodejs": {
    "subtitle": "Node.js",
    "about": "Node.js® is a platform built on Chrome's JavaScript runtime for easily building fast, scalable network applications. Node.js uses an event-driven, non-blocking I/O model that makes it lightweight and efficient, perfect for data-intensive real-time applications that run across distributed devices.",
    "site": "http://nodejs.org",
    "partners": [
      {
        "site" : "NodeCasts",
        "site_url": "http://nodecasts.net",
        "image": "nodecasts.jpg",
        "videos": [
          {
            "title": "Introduction to Node.js",
            "description": "What is Node.js and why might you want to use it?",
            "duration": "6:40",
            "url": "http://nodecasts.net/episodes/1-introduction-to-nodejs"
          },
          {
            "title": "Node.js First Steps",
            "description": "We'll learn out how to install Node.js, as well as how to maintain different Node versions using NVM. We'll also build a basic HTTP server.",
            "duration": "7:30",
            "url": "http://nodecasts.net/episodes/2-nodejs-first-steps"
          }
        ]
      }
    ]
  },
  "ruby": {
    "subtitle": "Ruby",
    "about": "Ruby is a dynamic, open source programming language with a focus on simplicity and productivity. It has an elegant syntax that is natural to read and easy to write.",
    "site": "https://www.ruby-lang.org",
    "partners": [
      {
        "site" : "GoRails",
        "site_url": "https://gorails.com/",
        "image": "gorails.jpg",
        "videos": [
          {
            "title": "Ruby Version Managers",
            "description": "Techniques for installing Ruby and managing different versions between applications.",
            "duration": "4:15",
            "url": "https://gorails.com/episodes/ruby-version-managers"
          },
          {
            "title": "Rails Application Structure",
            "description": "A look into the files and folders inside every Rails application and how they fit together.",
            "duration": "14:03",
            "url": "https://gorails.com/episodes/rails-application-structure"
          }
        ]
      }
    ]
  }
}